facebookreport/__init__.py
facebookreport/reportmaker.py
facebookreport-0.3.2.dist-info/METADATA
facebookreport-0.3.2.dist-info/RECORD
facebookreport-0.3.2.dist-info/WHEEL
facebookreport-0.3.2.dist-info/entry_points.txt
facebookreport-0.3.2.dist-info/top_level.txt
tests/__init__.py
tests/facebookreport_tests.py
